sayt/__init__.py
sayt/_version.py
sayt/api.py
sayt/compat.py
sayt/dataset.py
sayt/exc.py
sayt/logger.py
sayt/paths.py
sayt/tracker.py
sayt/utils.py
sayt/docs/__init__.py
sayt/tests/__init__.py
sayt/tests/helper.py
sayt/vendor/__init__.py
sayt/vendor/nested_logger.py
sayt/vendor/pytest_cov_helper.py
sayt-0.6.5.dist-info/AUTHORS.rst
sayt-0.6.5.dist-info/LICENSE.txt
sayt-0.6.5.dist-info/METADATA
sayt-0.6.5.dist-info/WHEEL
sayt-0.6.5.dist-info/top_level.txt
sayt-0.6.5.dist-info/RECORD
